paralaser/__init__.py
paralaser/binary_offsets.py
paralaser/embed.py
paralaser/lib/__init__.py
paralaser/lib/indexing.py
paralaser/lib/romanize_lc.py
paralaser/lib/text_processing.py
paralaser/mine_bitexts.py
paralaser/models.py
paralaser/nli.py
paralaser/paraphrase.py
paralaser/sent_classif.py
paralaser/similarity_search.py
paralaser/tools-external/fast
paralaser/tools-external/moses-tokenizer/share/nonbreaking_prefixes/nonbreaking_prefix.ca
paralaser/tools-external/moses-tokenizer/share/nonbreaking_prefixes/nonbreaking_prefix.cs
paralaser/tools-external/moses-tokenizer/share/nonbreaking_prefixes/nonbreaking_prefix.de
paralaser/tools-external/moses-tokenizer/share/nonbreaking_prefixes/nonbreaking_prefix.el
paralaser/tools-external/moses-tokenizer/share/nonbreaking_prefixes/nonbreaking_prefix.en
paralaser/tools-external/moses-tokenizer/share/nonbreaking_prefixes/nonbreaking_prefix.es
paralaser/tools-external/moses-tokenizer/share/nonbreaking_prefixes/nonbreaking_prefix.fi
paralaser/tools-external/moses-tokenizer/share/nonbreaking_prefixes/nonbreaking_prefix.fr
paralaser/tools-external/moses-tokenizer/share/nonbreaking_prefixes/nonbreaking_prefix.ga
paralaser/tools-external/moses-tokenizer/share/nonbreaking_prefixes/nonbreaking_prefix.hu
paralaser/tools-external/moses-tokenizer/share/nonbreaking_prefixes/nonbreaking_prefix.is
paralaser/tools-external/moses-tokenizer/share/nonbreaking_prefixes/nonbreaking_prefix.it
paralaser/tools-external/moses-tokenizer/share/nonbreaking_prefixes/nonbreaking_prefix.lt
paralaser/tools-external/moses-tokenizer/share/nonbreaking_prefixes/nonbreaking_prefix.lv
paralaser/tools-external/moses-tokenizer/share/nonbreaking_prefixes/nonbreaking_prefix.nl
paralaser/tools-external/moses-tokenizer/share/nonbreaking_prefixes/nonbreaking_prefix.pl
paralaser/tools-external/moses-tokenizer/share/nonbreaking_prefixes/nonbreaking_prefix.pt
paralaser/tools-external/moses-tokenizer/share/nonbreaking_prefixes/nonbreaking_prefix.ro
paralaser-0.2.dist-info/LICENSE
paralaser-0.2.dist-info/WHEEL
paralaser-0.2.dist-info/METADATA
paralaser-0.2.dist-info/RECORD
