Metadata-Version: 2.1
Name: paralaser
Version: 0.2
Summary: 
License: BSD-3-Clause
Requires-Python: >=3.8,<4.0
Classifier: License :: OSI Approved :: BSD License
Classifier: Programming Language :: Python :: 3
Classifier: Programming Language :: Python :: 3.8
Classifier: Programming Language :: Python :: 3.9
Requires-Dist: Cython (>=0.29.21,<0.30.0)
Requires-Dist: faiss-gpu (>=1.6.5,<2.0.0)
Requires-Dist: fastBPE (>=0.1.0,<0.2.0)
Requires-Dist: jieba (>=0.42.1,<0.43.0)
Requires-Dist: numpy (>=1.19.4,<2.0.0)
Requires-Dist: torch (>=1.7.1,<2.0.0)
Requires-Dist: transliterate (>=1.10.2,<2.0.0)
Requires-Dist: wget (>=3.2,<4.0)
